{
  "recipes": [
    {
      "id": "1",
      "title": "蔬菜燉湯",
      "ingredients": [
        "1 顆紅蘿蔔",
        "1 條韭菜",
        "200 克豆腐",
        "300 毫升蔬菜湯底"
      ],
      "method": "1. 將烤箱預熱至 200C/3C/煤氣 5。將紅蘿蔔、韭菜和豆腐放入大碗中。添加蔬菜湯底並充分攪拌。 2. 添加其餘的配料並充分攪拌。 3. 將混合物放入大碗中，蓋上蓋子。 4. 將蓋子放在烤箱中烹飪 40 分鐘。 5. 搭配您喜歡的沙拉一起享用。",
      "cookingTime": "45 分鐘"
    },
    {
      "id": "2",
      "title": "蔬菜比薩",
      "ingredients": [
        "1 塊餅底",
        "番茄泥",
        "1 個青椒",
        "100 克蘑菇"
      ],
      "method": "1. 將烤箱預熱至 200C/3C/煤氣 5。將番茄泥、青椒和蘑菇添加到餅底上。蓋上烤箱蓋烹飪 30 分鐘。 5. 搭配您喜歡的沙拉一起享用。",
      "cookingTime": "35 分鐘"
    },
    {
      "id": "3",
      "title": "希臘沙拉",
      "ingredients": [
        "1 顆洋蔥",
        "1 塊菲達乳酪",
        "橄欖",
        "番茄",
        "橄欖油"
      ],
      "method": "1. 將洋蔥、菲達乳酪、橄欖和番茄放入大碗中。 2. 加入橄欖油，輕輕拌勻。 3. 搭配您喜歡的主菜享用。",
      "cookingTime": "35 分鐘"
    },
    {
      "id": "4",
      "title": "紅燒豆腐",
      "ingredients": [
        "500克 豆腐",
        "100克 蔬菜",
        "適量 醬油",
        "適量 糖",
        "適量 料酒",
        "適量 鹽"
      ],
      "method": "1. 豆腐切塊，蔬菜準備好。 2. 鍋中加入適量油，放入蔬菜炒香。 3. 加入豆腐拌炒，並依次加入醬油、糖、料酒和鹽調味。 4. 炒至豆腐入味即可。 5. 用火腿煎熟即可。",
      "cookingTime": "25 分鐘"
    },
    {
      "id": "5",
      "title": "青椒肉絲",
      "ingredients": [
        "1 青椒",
        "200克 肉絲",
        "適量 蔥姜蒜",
        "適量 醬油",
        "適量 料酒",
        "適量 糖",
        "適量 鹽"
      ],
      "method": "1. 將青椒切絲，肉絲和調料準備好。 2. 燒熱鍋，放入油，熱油後放入蔥姜蒜爆香。 3. 放入肉絲炒至變色，加入調味料炒勻。 4. 最後加入青椒絲拌炒均勻即可。",
      "cookingTime": "20 分鐘"
    },
    {
      "id": "6",
      "title": "番茄炒蛋",
      "ingredients": [
        "2 顆番茄",
        "3 顆雞蛋",
        "適量 油",
        "適量 鹽",
        "適量 糖",
        "適量 蔥花"
      ],
      "method": "1. 番茄切塊，雞蛋打散，蔥花準備好。 2. 鍋中放入油，熱油後放入番茄塊翻炒至熟。 3. 放入打散的雞蛋，快速翻炒均勻。 4. 加入適量鹽和糖調味，最後撒上蔥花即可。",
      "cookingTime": "15 分鐘"
    }
  ]
}
